LICENSE
MANIFEST.in
README.rst
setup.py
proclib/__init__.py
proclib/api.py
proclib/helpers.py
proclib/pipe.py
proclib/process.py
proclib/response.py
proclib.egg-info/PKG-INFO
proclib.egg-info/SOURCES.txt
proclib.egg-info/dependency_links.txt
proclib.egg-info/not-zip-safe
proclib.egg-info/pbr.json
proclib.egg-info/requires.txt
proclib.egg-info/top_level.txt