Metadata-Version: 1.1
Name: proclib
Version: 0.1.3
Summary: pythonic processes
Home-page: https://github.com/datalib/proclib
Author: Eeo Jun
Author-email: packwolf58@gmail.com
License: MIT
Keywords: processes unix process datalib
Platform: any
Classifier: Development Status :: 4 - Beta
Classifier: Intended Audience :: Developers
Classifier: License :: OSI Approved :: MIT License
Classifier: Programming Language :: Python :: 2
Classifier: Programming Language :: Python :: 3
